gpt_j/Basic_api.py
gpt_j/Gptj.py
gpt_j/ImaginaryFriend.py
gpt_j/Text2TextGen.py
gpt_j/__init__.py
gpt_j/gptj_api.py
gptj-3.0.9.dist-info/LICENSE
gptj-3.0.9.dist-info/METADATA
gptj-3.0.9.dist-info/WHEEL
gptj-3.0.9.dist-info/top_level.txt
gptj-3.0.9.dist-info/RECORD
