Metadata-Version: 2.1
Name: gptj
Version: 3.0.9
Summary: A GPT-J api to use with python3 to generate text, blogs, code, and more (Note: Starting with version 3.0.7 the api is using the old domain again so there might be some issues with limits)
Home-page: https://github.com/TheProtaganist/gpt-j
Author: TheProtagonist (Michael Arana)
Author-email: MichaelGamer256@gmail.com
License: MIT
Keywords: python,text generation,chatbot framework,gpt-J,gpt-3,gpt-2,completion,code completion,language models,language model,nlp,natural language,natural language processing,meta-programming,story generation,story,API
Platform: UNKNOWN
Classifier: Development Status :: 5 - Production/Stable
Classifier: Natural Language :: English
Classifier: Intended Audience :: Developers
Classifier: Programming Language :: Python :: 3
Classifier: Programming Language :: Python :: 3.6
Classifier: Programming Language :: Python :: 3.7
Classifier: Programming Language :: Python :: 3.8
Classifier: Programming Language :: Python :: 3.9
Classifier: License :: OSI Approved :: MIT License
Classifier: Operating System :: Unix
Classifier: Operating System :: MacOS :: MacOS X
Classifier: Operating System :: Microsoft :: Windows
License-File: LICENSE
Requires-Dist: requests
